LICENSE
README.md
setup.py
cylibs/__init__.py
cylibs/rwlock.py
cylibs/sharepoint.py
cylibs/ver.py
cylibs.egg-info/PKG-INFO
cylibs.egg-info/SOURCES.txt
cylibs.egg-info/dependency_links.txt
cylibs.egg-info/not-zip-safe
cylibs.egg-info/requires.txt
cylibs.egg-info/top_level.txt