Metadata-Version: 2.1
Name: cylibs
Version: 1.4.0
Summary: Python libraries by ChihYing
Home-page: https://gitlab.com/chihyinglin/cylibs
Author: ChihYing_Lin
Author-email: 
License: MIT
Keywords: cylibs
Platform: UNKNOWN
Classifier: License :: OSI Approved :: MIT License
Classifier: Programming Language :: Python :: 3
Classifier: Topic :: Software Development :: Libraries
License-File: LICENSE
